stagehand/__init__.py
stagehand/_base_client.py
stagehand/_client.py
stagehand/_compat.py
stagehand/_constants.py
stagehand/_exceptions.py
stagehand/_files.py
stagehand/_models.py
stagehand/_qs.py
stagehand/_resource.py
stagehand/_response.py
stagehand/_streaming.py
stagehand/_types.py
stagehand/_version.py
stagehand/py.typed
stagehand/session.py
stagehand/_utils/__init__.py
stagehand/_utils/_compat.py
stagehand/_utils/_datetime_parse.py
stagehand/_utils/_logs.py
stagehand/_utils/_proxy.py
stagehand/_utils/_reflection.py
stagehand/_utils/_resources_proxy.py
stagehand/_utils/_streams.py
stagehand/_utils/_sync.py
stagehand/_utils/_transform.py
stagehand/_utils/_typing.py
stagehand/_utils/_utils.py
stagehand/lib/.keep
stagehand/lib/__init__.py
stagehand/lib/sea_binary.py
stagehand/lib/sea_server.py
stagehand/resources/__init__.py
stagehand/resources/sessions.py
stagehand/resources/sessions_helpers.py
stagehand/types/__init__.py
stagehand/types/action_param.py
stagehand/types/model_config_param.py
stagehand/types/session_act_params.py
stagehand/types/session_act_response.py
stagehand/types/session_end_response.py
stagehand/types/session_execute_params.py
stagehand/types/session_execute_response.py
stagehand/types/session_extract_params.py
stagehand/types/session_extract_response.py
stagehand/types/session_navigate_params.py
stagehand/types/session_navigate_response.py
stagehand/types/session_observe_params.py
stagehand/types/session_observe_response.py
stagehand/types/session_replay_response.py
stagehand/types/session_start_params.py
stagehand/types/session_start_response.py
stagehand/types/stream_event.py
stagehand/_sea/stagehand-darwin-x64
stagehand-3.5.0.dist-info/METADATA
stagehand-3.5.0.dist-info/WHEEL
stagehand-3.5.0.dist-info/licenses/LICENSE
stagehand-3.5.0.dist-info/RECORD
